digitick_client/__init__.py
digitick_client/api_client.py
digitick_client/configuration.py
digitick_client/rest.py
digitick_client/apis/__init__.py
digitick_client/apis/authorization_api.py
digitick_client/apis/catalog_api.py
digitick_client/apis/distribution_api.py
digitick_client/apis/document_api.py
digitick_client/apis/order_api.py
digitick_client/apis/user_api.py
digitick_client/apis/venue_api.py
digitick_client/models/__init__.py
digitick_client/models/auth_response.py
digitick_client/models/booking.py
digitick_client/models/booking_list_response.py
digitick_client/models/booking_ticket.py
digitick_client/models/booking_ticket_list.py
digitick_client/models/cart_add_by_seats_response.py
digitick_client/models/cart_add_response.py
digitick_client/models/cart_create_response.py
digitick_client/models/cart_entries_by_prices.py
digitick_client/models/cart_entries_by_seats.py
digitick_client/models/cart_entries_by_section.py
digitick_client/models/cart_response.py
digitick_client/models/category_response.py
digitick_client/models/category_response_inner.py
digitick_client/models/city.py
digitick_client/models/city_list.py
digitick_client/models/create_cart.py
digitick_client/models/date_time.py
digitick_client/models/delivery.py
digitick_client/models/delivery_mode.py
digitick_client/models/delivery_mode_list.py
digitick_client/models/department.py
digitick_client/models/entries_by_prices.py
digitick_client/models/entries_by_seats.py
digitick_client/models/entries_by_section.py
digitick_client/models/entries_cart_detail_response.py
digitick_client/models/entry.py
digitick_client/models/entry_list.py
digitick_client/models/error.py
digitick_client/models/events_response.py
digitick_client/models/events_response_inner.py
digitick_client/models/formats_response.py
digitick_client/models/grouping.py
digitick_client/models/grouping_list.py
digitick_client/models/groupings_response.py
digitick_client-0.1.0a4.dist-info/DESCRIPTION.rst
digitick_client-0.1.0a4.dist-info/METADATA
digitick_client-0.1.0a4.dist-info/RECORD
digitick_client-0.1.0a4.dist-info/WHEEL
digitick_client-0.1.0a4.dist-info/metadata.json
digitick_client-0.1.0a4.dist-info/top_level.txt
