Metadata-Version: 2.0
Name: digitick-client
Version: 0.1.0a4
Summary: An swagger-generated application providing an API access to digitick shopping websites
Home-page: https://github.com/frague59/digitick-client
Author: François GUÉRIN
Author-email: fguerin@ville-tourcoing.fr
License: MIT
Keywords: digitick swagger REST API
Platform: UNKNOWN
Classifier: Development Status :: 3 - Alpha
Classifier: Intended Audience :: Developers
Classifier: License :: OSI Approved :: MIT License
Classifier: Operating System :: POSIX :: Linux
Classifier: Topic :: Software Development :: Libraries
Classifier: Topic :: Utilities
Requires-Dist: certifi
Requires-Dist: urllib3
Requires-Dist: six
